{"home":"lnr lnr-home","apartment":"lnr lnr-apartment","pencil":"lnr lnr-pencil","magic-wand":"lnr lnr-magic-wand","drop":"lnr lnr-drop","lighter":"lnr lnr-lighter","poop":"lnr lnr-poop","sun":"lnr lnr-sun","moon":"lnr lnr-moon","cloud":"lnr lnr-cloud","cloud-upload":"lnr lnr-cloud-upload","cloud-download":"lnr lnr-cloud-download","cloud-sync":"lnr lnr-cloud-sync","cloud-check":"lnr lnr-cloud-check","database":"lnr lnr-database","lock":"lnr lnr-lock","cog":"lnr lnr-cog","trash":"lnr lnr-trash","dice":"lnr lnr-dice","heart":"lnr lnr-heart","star":"lnr lnr-star","star-half":"lnr lnr-star-half","star-empty":"lnr lnr-star-empty","flag":"lnr lnr-flag","envelope":"lnr lnr-envelope","paperclip":"lnr lnr-paperclip","inbox":"lnr lnr-inbox","eye":"lnr lnr-eye","printer":"lnr lnr-printer","file-empty":"lnr lnr-file-empty","file-add":"lnr lnr-file-add","enter":"lnr lnr-enter","exit":"lnr lnr-exit","graduation-hat":"lnr lnr-graduation-hat","license":"lnr lnr-license","music-note":"lnr lnr-music-note","film-play":"lnr lnr-film-play","camera-video":"lnr lnr-camera-video","camera":"lnr lnr-camera","picture":"lnr lnr-picture","book":"lnr lnr-book","bookmark":"lnr lnr-bookmark","user":"lnr lnr-user","users":"lnr lnr-users","shirt":"lnr lnr-shirt","store":"lnr lnr-store","cart":"lnr lnr-cart","tag":"lnr lnr-tag","phone-handset":"lnr lnr-phone-handset","phone":"lnr lnr-phone","pushpin":"lnr lnr-pushpin","map-marker":"lnr lnr-map-marker","map":"lnr lnr-map","location":"lnr lnr-location","calendar-full":"lnr lnr-calendar-full","keyboard":"lnr lnr-keyboard","spell-check":"lnr lnr-spell-check","screen":"lnr lnr-screen","smartphone":"lnr lnr-smartphone","tablet":"lnr lnr-tablet","laptop":"lnr lnr-laptop","laptop-phone":"lnr lnr-laptop-phone","power-switch":"lnr lnr-power-switch","bubble":"lnr lnr-bubble","heart-pulse":"lnr lnr-heart-pulse","construction":"lnr lnr-construction","pie-chart":"lnr lnr-pie-chart","chart-bars":"lnr lnr-chart-bars","gift":"lnr lnr-gift","diamond":"lnr lnr-diamond","linearicons":"lnr lnr-linearicons","dinner":"lnr lnr-dinner","coffee-cup":"lnr lnr-coffee-cup","leaf":"lnr lnr-leaf","paw":"lnr lnr-paw","rocket":"lnr lnr-rocket","briefcase":"lnr lnr-briefcase","bus":"lnr lnr-bus","car":"lnr lnr-car","train":"lnr lnr-train","bicycle":"lnr lnr-bicycle","wheelchair":"lnr lnr-wheelchair","select":"lnr lnr-select","earth":"lnr lnr-earth","smile":"lnr lnr-smile","sad":"lnr lnr-sad","neutral":"lnr lnr-neutral","mustache":"lnr lnr-mustache","alarm":"lnr lnr-alarm","bullhorn":"lnr lnr-bullhorn","volume-high":"lnr lnr-volume-high","volume-medium":"lnr lnr-volume-medium","volume-low":"lnr lnr-volume-low","volume":"lnr lnr-volume","mic":"lnr lnr-mic","hourglass":"lnr lnr-hourglass","undo":"lnr lnr-undo","redo":"lnr lnr-redo","sync":"lnr lnr-sync","history":"lnr lnr-history","clock":"lnr lnr-clock","download":"lnr lnr-download","upload":"lnr lnr-upload","enter-down":"lnr lnr-enter-down","exit-up":"lnr lnr-exit-up","bug":"lnr lnr-bug","code":"lnr lnr-code","link":"lnr lnr-link","unlink":"lnr lnr-unlink","thumbs-up":"lnr lnr-thumbs-up","thumbs-down":"lnr lnr-thumbs-down","magnifier":"lnr lnr-magnifier","cross":"lnr lnr-cross","menu":"lnr lnr-menu","list":"lnr lnr-list","chevron-up":"lnr lnr-chevron-up","chevron-down":"lnr lnr-chevron-down","chevron-left":"lnr lnr-chevron-left","chevron-right":"lnr lnr-chevron-right","arrow-up":"lnr lnr-arrow-up","arrow-down":"lnr lnr-arrow-down","arrow-left":"lnr lnr-arrow-left","arrow-right":"lnr lnr-arrow-right","move":"lnr lnr-move","warning":"lnr lnr-warning","question-circle":"lnr lnr-question-circle","menu-circle":"lnr lnr-menu-circle","checkmark-circle":"lnr lnr-checkmark-circle","cross-circle":"lnr lnr-cross-circle","plus-circle":"lnr lnr-plus-circle","circle-minus":"lnr lnr-circle-minus","arrow-up-circle":"lnr lnr-arrow-up-circle","arrow-down-circle":"lnr lnr-arrow-down-circle","arrow-left-circle":"lnr lnr-arrow-left-circle","arrow-right-circle":"lnr lnr-arrow-right-circle","chevron-up-circle":"lnr lnr-chevron-up-circle","chevron-down-circle":"lnr lnr-chevron-down-circle","chevron-left-circle":"lnr lnr-chevron-left-circle","chevron-right-circle":"lnr lnr-chevron-right-circle","crop":"lnr lnr-crop","frame-expand":"lnr lnr-frame-expand","frame-contract":"lnr lnr-frame-contract","layers":"lnr lnr-layers","funnel":"lnr lnr-funnel","text-format":"lnr lnr-text-format","text-format-remove":"lnr lnr-text-format-remove","text-size":"lnr lnr-text-size","bold":"lnr lnr-bold","italic":"lnr lnr-italic","underline":"lnr lnr-underline","strikethrough":"lnr lnr-strikethrough","highlight":"lnr lnr-highlight","text-align-left":"lnr lnr-text-align-left","text-align-center":"lnr lnr-text-align-center","text-align-right":"lnr lnr-text-align-right","text-align-justify":"lnr lnr-text-align-justify","line-spacing":"lnr lnr-line-spacing","indent-increase":"lnr lnr-indent-increase","indent-decrease":"lnr lnr-indent-decrease","pilcrow":"lnr lnr-pilcrow","direction-ltr":"lnr lnr-direction-ltr","direction-rtl":"lnr lnr-direction-rtl","page-break":"lnr lnr-page-break","sort-alpha-asc":"lnr lnr-sort-alpha-asc","sort-amount-asc":"lnr lnr-sort-amount-asc","hand":"lnr lnr-hand","pointer-up":"lnr lnr-pointer-up","pointer-right":"lnr lnr-pointer-right","pointer-down":"lnr lnr-pointer-down","pointer-left":"lnr lnr-pointer-left"}